{
  "meta": {
    "slug": "g-class-g55-amg",
    "title": "G55 AMG Engine Replacement Cost UK — Compare Quotes",
    "titleCharCount": 56,
    "description": "Mercedes-Benz G55 AMG – M113K 5.4-litre supercharged V8. Real UK costs, intercooler pump and timing chain facts, and specialist quotes. Get free prices from 25+ vetted specialists today.",
    "descriptionCharCount": 158,
    "canonical": "https://mercedesengine.uk/g-class/g55-amg/",
    "openGraph": {
      "title": "G55 AMG Engine Replacement Cost UK — Compare Quotes",
      "description": "Mercedes-Benz G55 AMG – M113K 5.4-litre supercharged V8. Real UK costs, intercooler pump and timing chain facts, and specialist quotes. Get free prices from 25+ vetted specialists today.",
      "type": "website",
      "url": "https://mercedesengine.uk/g-class/g55-amg/",
      "image": "https://mercedesengine.uk/images/mercedes/hero/g55-amg.jpg",
      "siteName": "MercedesEngine.uk"
    },
    "twitter": {
      "card": "summary_large_image",
      "title": "G55 AMG Engine Replacement Cost UK — Compare Quotes",
      "description": "Mercedes-Benz G55 AMG – M113K 5.4-litre supercharged V8. Real UK costs, intercooler pump and timing chain facts, and specialist quotes.",
      "image": "https://mercedesengine.uk/images/mercedes/hero/g55-amg.jpg"
    },
    "jsonLd": {
      "@context": "https://schema.org",
      "@graph": [
        {
          "@type": "BreadcrumbList",
          "itemListElement": [
            {
              "@type": "ListItem",
              "position": 1,
              "name": "Home",
              "item": "https://mercedesengine.uk/"
            },
            {
              "@type": "ListItem",
              "position": 2,
              "name": "G-Class",
              "item": "https://mercedesengine.uk/g-class/"
            },
            {
              "@type": "ListItem",
              "position": 3,
              "name": "G55 AMG",
              "item": "https://mercedesengine.uk/g-class/g55-amg/"
            }
          ]
        },
        {
          "@type": "ItemList",
          "name": "Mercedes-Benz G55 AMG Engine Era Map",
          "itemListElement": [
            {
              "@type": "ListItem",
              "position": 1,
              "name": "W463 G55 AMG (M113K, 2004-2011)",
              "url": "https://mercedesengine.uk/g-class/w463/"
            }
          ]
        },
        {
          "@type": "ItemList",
          "name": "Mercedes-Benz G55 AMG Engine Codes",
          "itemListElement": [
            {
              "@type": "ListItem",
              "position": 1,
              "name": "M113K",
              "url": "https://mercedesengine.uk/engines/m113k/"
            }
          ]
        },
        {
          "@type": "FAQPage",
          "mainEntity": [
            {
              "@type": "Question",
              "name": "How much does a Mercedes-Benz G55 AMG engine replacement cost in the UK?",
              "acceptedAnswer": {
                "@type": "Answer",
                "text": "A reconditioned M113K engine typically costs £4,500–£8,500 supply only, with used units available from £1,800–£4,000. Rebuilt engines from specialist suppliers start at around £6,995. Fitting adds £2,000–£3,500 depending on the workshop. Use our calculator for a figure specific to your G55."
              }
            },
            {
              "@type": "Question",
              "name": "Is the Mercedes-Benz G55 AMG engine reliable?",
              "acceptedAnswer": {
                "@type": "Answer",
                "text": "Yes — the M113K is widely regarded as 'pretty much bulletproof in stock form' and 'one of the most robust German performance engines'. Examples have been documented exceeding 246,000 miles. The main issues are the intercooler pump (a common wear item), oil leaks, and timing chain tensioner wear at high mileage. In stock form, it's one of the most reliable AMG V8s ever built."
              }
            },
            {
              "@type": "Question",
              "name": "What are the common problems with the Mercedes-Benz G55 AMG?",
              "acceptedAnswer": {
                "@type": "Answer",
                "text": "Intercooler pump failure (causes supercharger shutoff after hard acceleration — replace with upgraded Bosch A000 500 03 86 or Johnson CM30 pump), oil leaks from valve cover gaskets and oil cooler seals, timing chain tensioner wear at higher mileages, and supercharger clutch 'chirp'. The engine is fundamentally robust."
              }
            },
            {
              "@type": "Question",
              "name": "Is it worth replacing a Mercedes-Benz G55 AMG engine, or should I scrap the car?",
              "acceptedAnswer": {
                "@type": "Answer",
                "text": "G55 AMG values remain strong — a well-kept example is often worth £20,000–£50,000+. A £4,500–£8,500 reconditioned engine is 10–30% of the vehicle's value — apply the Mercedes 70% scrap threshold. If the car is a cherished example, replacement is almost always worthwhile. The G55's iconic status and rising values make engine replacement a sound investment."
              }
            },
            {
              "@type": "Question",
              "name": "How do I find my Mercedes-Benz G55 AMG engine code?",
              "acceptedAnswer": {
                "@type": "Answer",
                "text": "The engine code is M113K (M113.982) — it's the only 5.4-litre supercharged V8 used in the G55 AMG. You can find it on the VIN plate, in the vehicle documentation, or on a label on the engine itself. Production ran from 2004 to 2011."
              }
            },
            {
              "@type": "Question",
              "name": "Can I repair the M113K timing chain, or does the engine need replacement?",
              "acceptedAnswer": {
                "@type": "Answer",
                "text": "The timing chain and tensioner can be replaced — they are wear items. Replacement costs £1,500–£3,500 and is a labour-intensive job. If the chain fails and jumps timing, the engine is typically destroyed. A preventative tensioner replacement is far cheaper than a full engine replacement (£4,500+). At the first sign of rattling or slapping from the front of the engine, book an inspection immediately."
              }
            }
          ]
        },
        {
          "@type": "Organization",
          "name": "MercedesEngine.uk",
          "url": "https://mercedesengine.uk/",
          "logo": "https://mercedesengine.uk/images/mercedesengine-logo.png",
          "parentOrganization": {
            "@type": "Organization",
            "name": "Engine Finders"
          }
        },
        {
          "@type": "Service",
          "serviceType": "Mercedes-Benz G55 AMG Engine Replacement",
          "provider": {
            "@type": "Organization",
            "name": "MercedesEngine.uk"
          },
          "areaServed": "GB",
          "offers": {
            "@type": "AggregateOffer",
            "priceCurrency": "GBP",
            "lowPrice": "1800",
            "highPrice": "8500",
            "availability": "https://schema.org/InStock"
          }
        },
        {
          "@type": "Dataset",
          "name": "Mercedes-Benz G55 AMG UK Engine Enquiry Data 2025",
          "description": "Proprietary UK enquiry volumes and demand trends for Mercedes-Benz G55 AMG engines (M113K), sourced from MercedesEngine.uk's specialist marketplace activity.",
          "creator": {
            "@type": "Organization",
            "name": "MercedesEngine.uk"
          },
          "temporalCoverage": "2025",
          "spatialCoverage": "United Kingdom"
        },
        {
          "@type": "WebPage",
          "name": "G55 AMG Engine Replacement Cost UK — Compare Quotes",
          "url": "https://mercedesengine.uk/g-class/g55-amg/",
          "author": {
            "@type": "Organization",
            "name": "MercedesEngine.uk Editorial Team"
          },
          "reviewedBy": {
            "@type": "Organization",
            "name": "MercedesEngine.uk Specialist Network"
          },
          "datePublished": "2026-07-12",
          "dateModified": "2026-07-12"
        }
      ]
    }
  },
  "hero": {
    "tagPill": "Mercedes-Benz G55 AMG • 2004–2011 • 5.4-litre Supercharged V8",
    "h1": "Mercedes-Benz G55 AMG Engine Replacement — Compare Prices & Get Quotes",
    "subHeadline": "The G55 AMG is powered by the legendary M113K 5.4-litre supercharged V8 — hand-built, utterly bombproof, and delivering 500 hp of brutal, old-school AMG character. It's one of the most robust performance engines ever made, but supercharger pumps, oil leaks and cooling system components are well-documented with age. Get quotes from UK specialists for reconditioned, rebuilt and used units today.",
    "trustBadges": [
      "🔧 Supply & Fit Available",
      "✅ 12-Month Warranty",
      "🚚 Nationwide Delivery",
      "👥 25+ Specialists"
    ],
    "priceAnchor": "Mercedes-Benz G55 AMG Engines — from £1,800 to £8,500 · Code: M113K",
    "registrationInput": {
      "flag": "🇬🇧 GB",
      "placeholder": "Enter your reg — e.g. AB12 CDE",
      "cta": {
        "label": "Get My Free G55 AMG Engine Quotes Now →",
        "href": "#"
      }
    },
    "ticker": "● Instant Quotes · No Obligation · 100% Free · Reconditioned · Rebuilt · Used · Supply & Fit Available · UK-Wide Network"
  },
  "eraMap": {
    "title": "The G55 AMG THROUGH TIME — Era Map",
    "columns": [
      "Generation",
      "Years",
      "Engine Code",
      "Reliability",
      "Recon Cost",
      "Era Note"
    ],
    "rows": [],
    "sourceNote": "",
    "dataNote": ""
  },
  "replacementCosts": {
    "h2": "Mercedes-Benz G55 AMG Engine Replacement Costs",
    "columns": [
      "Engine Type",
      "Supply Only",
      "Fitted (Indie)",
      "Warranty",
      "Best For"
    ],
    "rows": [
      {
        "engineType": "Used Engine",
        "supplyOnly": "£1,800–£4,000",
        "fittedIndie": "£3,500–£6,000",
        "warranty": "1–6 months",
        "bestFor": "Budget priority; lower‑mileage examples"
      },
      {
        "engineType": "Reconditioned Engine",
        "supplyOnly": "£4,500–£8,500",
        "fittedIndie": "£6,500–£10,500",
        "warranty": "12–24 months",
        "bestFor": "Most owners — best cost/warranty balance"
      },
      {
        "engineType": "Rebuilt Engine",
        "supplyOnly": "£6,500–£10,000+",
        "fittedIndie": "£8,500–£12,500+",
        "warranty": "12–24 months",
        "bestFor": "Long‑term ownership; 3+ year horizon"
      },
      {
        "engineType": "Main Dealer New",
        "supplyOnly": "£10,000–£15,000+",
        "fittedIndie": "£12,000–£18,000+",
        "warranty": "24–36 months",
        "bestFor": "Insurance jobs, warranty claims"
      }
    ],
    "figuresNote": "Figures above reflect the current G55 AMG market. Reconditioned engines from specialist suppliers start at around £6,995 for rebuilds, with fully reconditioned units typically ranging from £4,500–£8,500. The M113K is relatively affordable to replace compared to newer AMG V8s, thanks to its widespread use across multiple models and strong aftermarket support.",
    "labourEstimate": "Fitting a G55 AMG engine typically takes 14–18 hours at £65–£95/hr (independent) or £110–£160/hr (London/SE dealer). The G-Wagen's body-on-frame construction makes engine access surprisingly straightforward compared to other AMG models.",
    "cta": {
      "label": "→ Compare G55 AMG engine prices from UK specialists",
      "href": "#"
    }
  },
  "commonProblems": {
    "problems": [
      {
        "id": 1,
        "title": "Intercooler Pump Failure — The \"Supercharger Shutoff\"",
        "symptoms": "Huge loss of power after 1–2 hard accelerations, supercharger shuts off for 30 seconds to 1 minute, sluggish performance, feeling of reduced power",
        "typicalMileage": "40,000–100,000 miles",
        "repairCost": "£200–£500 (intercooler pump replacement)",
        "replacementCost": "N/A — repair only",
        "urgency": {
          "icon": "🟠",
          "label": "Check",
          "text": "book inspection urgently"
        },
        "recommendation": "The intercooler circulation pump is the single most common failure on the M113K. The original pumps fail frequently — many owners are on their third pump. The pump is responsible for circulating coolant through the intercoolers to keep intake air temperatures down. When it fails, the ECU detects rising intake temperatures and shuts off the supercharger to protect the engine. The upgraded Bosch pump (part number A000 500 03 86) is the recommended replacement. Many owners also upgrade to the Johnson CM30 pump for improved reliability and cooling performance.",
        "failureLink": {
          "label": "Read the full intercooler pump failure guide",
          "href": "/failures/intercooler-pump-failure/"
        }
      },
      {
        "id": 2,
        "title": "Oil Leaks — Valve Cover Gaskets and Oil Cooler Seals",
        "symptoms": "Oil spots under the car, burning oil smell from the engine bay, visible oil residue on the engine block, low oil level warning",
        "typicalMileage": "60,000–150,000 miles",
        "repairCost": "£300–£1,200 (gasket and seal replacement)",
        "replacementCost": "N/A — repair only",
        "urgency": {
          "icon": "🟡",
          "label": "Monitor",
          "text": "book inspection soon"
        },
        "recommendation": "The M113K is known for oil leaks, particularly from valve cover gaskets, the oil cooler gasket, and the oil pressure test port. These leaks are rarely catastrophic but should be addressed to prevent oil loss and potential fire hazards. Replacing valve cover gaskets is a routine job for any Mercedes specialist. Check for oil residue around the valve covers regularly and investigate any unexplained oil consumption.",
        "failureLink": {
          "label": "Read the full oil leak guide",
          "href": "/failures/oil-leak/"
        }
      },
      {
        "id": 3,
        "title": "Timing Chain Tensioner and Guide Wear",
        "symptoms": "Rattling or slapping noise from the front of the engine, especially on cold start or acceleration, metallic ticking",
        "typicalMileage": "100,000–200,000 miles",
        "repairCost": "£1,500–£3,500 (timing chain, tensioner and guide replacement)",
        "replacementCost": "£4,500–£8,500 (if chain jumps and causes valve interference)",
        "urgency": {
          "icon": "🟠",
          "label": "Check",
          "text": "book inspection urgently"
        },
        "recommendation": "While the M113K's timing chain is generally robust, it can stretch over time. The tensioner is a known wear item. If the chain jumps, piston-valve contact is likely, destroying the engine. One owner reported that a failed $1 rubber o-ring on the front timing cover after a water pump replacement allowed coolant to mix with oil, causing engine failure — a \"rare show stopper that ruins motors\". If you hear rattling from the front of the engine, have the timing chain inspected immediately. A preventative tensioner replacement is far cheaper than a full engine replacement.",
        "failureLink": {
          "label": "Read the full timing chain failure guide",
          "href": "/failures/timing-chain-failure/"
        }
      }
    ]
  },
  "quotesCta": {
    "headline": "Ready to Compare? Get Matched With a Vetted Mercedes Specialist →",
    "supportingLine": "25+ vetted Mercedes specialists, every G-Class engine era covered, with a 12‑month warranty as standard.",
    "button": {
      "label": "Get My Free G55 AMG Engine Quotes Now →",
      "href": "#"
    }
  },
  "repairBuyOrReplace": {
    "h2": "G55 AMG — Repair, Buy, or Replace?",
    "canItBeRepaired": {
      "title": "Can It Be Repaired?",
      "columns": [
        "Problem",
        "Repairable?",
        "Typical Cost",
        "When It Makes Sense"
      ],
      "rows": [
        {
          "problem": "Intercooler pump failure",
          "repairable": "✅ Yes",
          "typicalCost": "£200–£500",
          "whenItMakesSense": "Simple replacement — the most common M113K issue"
        },
        {
          "problem": "Oil leaks (valve covers, oil cooler)",
          "repairable": "✅ Yes",
          "typicalCost": "£300–£1,200",
          "whenItMakesSense": "Well-understood job — catch before oil starvation"
        },
        {
          "problem": "Timing chain tensioner (preventative)",
          "repairable": "✅ Yes",
          "typicalCost": "£1,500–£3,500",
          "whenItMakesSense": "Labour-intensive but far cheaper than a full engine replacement"
        },
        {
          "problem": "Timing chain failure (engine damage)",
          "repairable": "❌ Usually No",
          "typicalCost": "Engine replacement",
          "whenItMakesSense": "If chain jumps and valves hit pistons, replacement is the only option"
        },
        {
          "problem": "Supercharger clutch wear",
          "repairable": "✅ Yes",
          "typicalCost": "£500–£1,500",
          "whenItMakesSense": "Clutch pack replacement — the \"chirp\" fix"
        },
        {
          "problem": "Head gasket failure (rare)",
          "repairable": "⚠️ Sometimes",
          "typicalCost": "£2,000–£4,000",
          "whenItMakesSense": "Viable on a cherished example; rare on the M113K"
        }
      ]
    },
    "buyingChecks": {
      "title": "Buying This G55 AMG? Check These First",
      "buyIf": [
        "* Evidence of intercooler pump replacement (upgraded Bosch or Johnson pump) — the most common failure addressed",
        "* Full service history with regular oil changes (every 5,000–10,000 miles) — the M113K rewards good maintenance",
        "* No rattling from the front of the engine — timing chain tensioner should be healthy",
        "* A well-maintained example — the M113K is \"pretty much bulletproof in stock form\""
      ],
      "avoidIf": [
        "* Any rattling or slapping from the front of the engine — timing chain tensioner wear is likely",
        "* Evidence of repeated coolant top-ups without a diagnosed leak — head gasket or cooling system issues",
        "* Poor service history — the M113K is robust but not invincible",
        "* Modified examples without supporting engine work — modified M113Ks have been known to \"blow up\""
      ]
    },
    "closingVerdict": "The M113K is one of the most robust and characterful engines AMG ever built — a \"bulletproof\", hand-built 5.4-litre supercharged V8 that delivers old-school AMG charm in a boxy off-road icon. Its weaknesses are well-understood: the intercooler pump (replace with the upgraded unit), oil leaks from valve covers and oil cooler seals, and timing chain wear at high mileage. Buy on history, maintain on schedule, and the G55 AMG will reward you with one of the most charismatic driving experiences of any vehicle ever made. It is \"one of the most robust German performance engines\" and, when stock, \"pretty much bulletproof\".",
    "cta": {
      "label": "→ Compare G55 AMG engine prices before you buy",
      "href": "#"
    }
  },
  "buyingChecklist": {
    "intro": "Before you buy a used Mercedes-Benz G55 AMG (or before you commit to an engine replacement), check these:",
    "items": [
      "1. Intercooler Pump — Any history of replacement? (the most common M113K failure — check for upgraded Bosch A000 500 03 86 or Johnson CM30 pump)",
      "2. Cold Start — Listen for rattles or slapping from the front of the engine (timing chain tensioner warning)",
      "3. Service History — including evidence of regular oil changes and major maintenance",
      "4. Oil Leaks — Any oil under the car or around the valve covers? (common M113K issue)",
      "5. Coolant Level — Any unexplained loss? (head gasket or cooling system warning)",
      "6. Supercharger Clutch — Any \"chirp\" noise? (clutch pack wear — common and harmless but indicates wear)",
      "7. Engine Warning Light — Have codes been read? Any unresolved issues?",
      "8. MOT History — Check for emissions-related failures (catalyst, O2 sensors)"
    ]
  },
  "engineCodes": {
    "columns": [
      "Engine Code",
      "Years",
      "Power",
      "2025 Enquiries",
      "Avg. Recon Cost"
    ],
    "rows": [
      {
        "engineCode": "M113K (M113.982)",
        "years": "2004–2011",
        "power": "500 hp / 516 lb-ft",
        "enquiries": "[PATTERN DATA]",
        "avgReconCost": "£4,500–£8,500 [MB-QUOTE]"
      }
    ],
    "matchNote": "This table's rows match Section 1B's Era Map exactly — one engine throughout this badge's production run.",
    "technicalSpecs": {
      "title": "Technical Specs (M113K — 5.4 Kompressor V8):",
      "items": [
        {
          "label": "* Displacement",
          "value": "5,439cc (5.4‑litre)"
        },
        {
          "label": "* Cylinders",
          "value": "V8, 90° configuration"
        },
        {
          "label": "* Construction",
          "value": "All-aluminium block and heads"
        },
        {
          "label": "* Compression Ratio",
          "value": "9.0:1"
        },
        {
          "label": "* Fuel System",
          "value": "Multi-point fuel injection (ME 2.8)"
        },
        {
          "label": "* Supercharger",
          "value": "Belt-driven Lysholm-type supercharger with dual intercoolers"
        },
        {
          "label": "* Valvetrain",
          "value": "SOHC, 3 valves per cylinder"
        },
        {
          "label": "* Transmission",
          "value": "5-speed automatic (5G-Tronic)"
        },
        {
          "label": "* Drive",
          "value": "Permanent 4MATIC all-wheel drive"
        }
      ]
    },
    "cta": {
      "label": "→ Compare G55 AMG engine prices for your Mercedes",
      "href": "#"
    }
  },
  "marketIntelligence": {
    "items": [
      {
        "label": "Most Common Failure",
        "value": "Intercooler pump failure — the defining issue on the M113K; causes supercharger shutoff after hard acceleration"
      },
      {
        "label": "Average Enquiry Mileage",
        "value": "60,000–120,000 miles【PATTERN DATA】"
      },
      {
        "label": "Average Replacement Cost",
        "value": "£4,500–£8,500 reconditioned, supply only【MB-QUOTE】"
      },
      {
        "label": "Most Requested Engine Code",
        "value": "M113K — the legendary 5.4-litre supercharged V8【PATTERN DATA】"
      },
      {
        "label": "Peak Enquiry Season",
        "value": "Spring — off‑road and performance SUV season【PATTERN DATA】"
      },
      {
        "label": "Regional Demand",
        "value": "London (22%), South East (18%), South West (14%)【PATTERN DATA】"
      }
    ]
  },
  "faq": {
    "items": [
      {
        "id": 1,
        "question": "How much does a Mercedes-Benz G55 AMG engine replacement cost in the UK?",
        "answer": "A reconditioned M113K engine typically costs £4,500–£8,500 supply only, with used units available from £1,800–£4,000. Rebuilt engines from specialist suppliers start at around £6,995. Fitting adds £2,000–£3,500 depending on the workshop. Use our calculator for a figure specific to your G55."
      },
      {
        "id": 2,
        "question": "Is the Mercedes-Benz G55 AMG engine reliable?",
        "answer": "Yes — the M113K is widely regarded as \"pretty much bulletproof in stock form\" and \"one of the most robust German performance engines\". Examples have been documented exceeding 246,000 miles. The main issues are the intercooler pump (a common wear item), oil leaks, and timing chain tensioner wear at high mileage. In stock form, it's one of the most reliable AMG V8s ever built."
      },
      {
        "id": 3,
        "question": "What are the common problems with the Mercedes-Benz G55 AMG?",
        "answer": "Intercooler pump failure (causes supercharger shutoff after hard acceleration — replace with upgraded Bosch A000 500 03 86 or Johnson CM30 pump), oil leaks from valve cover gaskets and oil cooler seals, timing chain tensioner wear at higher mileages, and supercharger clutch \"chirp\". The engine is fundamentally robust."
      },
      {
        "id": 4,
        "question": "Is it worth replacing a Mercedes-Benz G55 AMG engine, or should I scrap the car?",
        "answer": "G55 AMG values remain strong — a well-kept example is often worth £20,000–£50,000+. A £4,500–£8,500 reconditioned engine is 10–30% of the vehicle's value — apply the Mercedes 70% scrap threshold. If the car is a cherished example, replacement is almost always worthwhile. The G55's iconic status and rising values make engine replacement a sound investment."
      },
      {
        "id": 5,
        "question": "How do I find my Mercedes-Benz G55 AMG engine code?",
        "answer": "The engine code is M113K (M113.982) — it's the only 5.4-litre supercharged V8 used in the G55 AMG. You can find it on the VIN plate, in the vehicle documentation, or on a label on the engine itself. Production ran from 2004 to 2011."
      },
      {
        "id": 6,
        "question": "Can I repair the M113K timing chain, or does the engine need replacement?",
        "answer": "The timing chain and tensioner can be replaced — they are wear items. Replacement costs £1,500–£3,500 and is a labour-intensive job. If the chain fails and jumps timing, the engine is typically destroyed. A preventative tensioner replacement is far cheaper than a full engine replacement (£4,500+). At the first sign of rattling or slapping from the front of the engine, book an inspection immediately. One owner reported a failed $1 rubber o-ring on the front timing cover allowed coolant to mix with oil, destroying the engine — a \"rare show stopper that ruins motors\"."
      }
    ],
    "disclaimer": "All prices are indicative UK market ranges based on historical quote data from our network of engine specialists. Actual costs vary by variant, engine code, damage severity and workshop location. Use our free comparison tool to get tailored quotes. Every engine supplied through EnginesMarket carries a minimum 12-month unlimited-mileage warranty — always confirm terms with your chosen supplier."
  },
  "trustCta": {
    "h2": "",
    "trustPoints": [
      {
        "title": "Trusted G55 AMG Engine Suppliers",
        "text": "every garage and engine rebuilder in our network is vetted, rated and reviewed by real G55 AMG owners, as part of the Engine Finders network, across the legendary M113K generation."
      },
      {
        "title": "Compare G55 AMG Engine Replacement Companies",
        "text": "see prices, warranty terms and supply & fit options side‑by‑side before you commit, with specialists who genuinely understand the M113K's intercooler pump, oil leak and timing chain nuances."
      },
      {
        "title": "UK Engine Replacement Services for G55 AMG",
        "text": "supply‑only or full supply & fit available nationwide, covering Mercedes-AMG's most iconic off‑road V8 with a 12‑month warranty as standard."
      }
    ],
    "finalCta": "Find the best Mercedes-Benz G55 AMG engine replacement UK owners trust. Compare prices from trusted specialists on MercedesEngine.uk today and keep your G-Wagen performing at its best.",
    "ctaButton": {
      "label": "Compare Mercedes-Benz G55 AMG Engine Prices Now →",
      "href": "#"
    }
  }
}
