{
  "meta": {
    "slug": "slc-slc180-200",
    "title": "Mercedes SLC 180 / 200 Engine Replacement Cost UK — Compare Quotes",
    "titleCharCount": 60,
    "description": "Every Mercedes SLC 180/200 engine — 1.6L and 2.0L M274 turbo four-cylinders. Real UK costs, timing chain and PCV advice, and honest reliability data. Get free quotes from 25+ vetted Mercedes specialists today.",
    "descriptionCharCount": 158,
    "canonical": "https://mercedesengine.uk/slc/slc180-200/",
    "openGraph": {
      "title": "Mercedes SLC 180 / 200 Engine Replacement Cost UK — Compare Quotes",
      "description": "Every Mercedes SLC 180/200 engine — 1.6L and 2.0L M274 turbo four-cylinders. Real UK costs, timing chain and PCV advice, and honest reliability data. Get free quotes from 25+ vetted Mercedes specialists today.",
      "type": "website",
      "url": "https://mercedesengine.uk/slc/slc180-200/",
      "image": "https://mercedesengine.uk/images/mercedes/hero/slc180-200.jpg",
      "siteName": "MercedesEngine.uk"
    },
    "twitter": {
      "card": "summary_large_image",
      "title": "Mercedes SLC 180 / 200 Engine Replacement Cost UK — Compare Quotes",
      "description": "Every Mercedes SLC 180/200 engine — 1.6L and 2.0L M274 turbo four-cylinders. Real UK costs, timing chain and PCV advice, and honest reliability data.",
      "image": "https://mercedesengine.uk/images/mercedes/hero/slc180-200.jpg"
    },
    "jsonLd": {
      "@context": "https://schema.org",
      "@graph": [
        {
          "@type": "BreadcrumbList",
          "itemListElement": [
            {
              "@type": "ListItem",
              "position": 1,
              "name": "Home",
              "item": "https://mercedesengine.uk/"
            },
            {
              "@type": "ListItem",
              "position": 2,
              "name": "SLC",
              "item": "https://mercedesengine.uk/slc/"
            },
            {
              "@type": "ListItem",
              "position": 3,
              "name": "R172",
              "item": "https://mercedesengine.uk/slc/r172/"
            },
            {
              "@type": "ListItem",
              "position": 4,
              "name": "SLC 180 / 200",
              "item": "https://mercedesengine.uk/slc/slc180-200/"
            }
          ]
        },
        {
          "@type": "ItemList",
          "name": "Mercedes SLC 180 / 200 Engine Era Map",
          "itemListElement": [
            {
              "@type": "ListItem",
              "position": 1,
              "name": "R172 SLC 180 (M274.910, 1.6L, 156 hp, 2016–2020)",
              "url": "https://mercedesengine.uk/slc/r172/"
            },
            {
              "@type": "ListItem",
              "position": 2,
              "name": "R172 SLC 200 (M274.920, 2.0L, 184 hp, 2016–2020)",
              "url": "https://mercedesengine.uk/slc/r172/"
            }
          ]
        },
        {
          "@type": "ItemList",
          "name": "Mercedes SLC 180 / 200 Engine Codes",
          "itemListElement": [
            {
              "@type": "ListItem",
              "position": 1,
              "name": "M274.910",
              "url": "https://mercedesengine.uk/engines/m274/"
            },
            {
              "@type": "ListItem",
              "position": 2,
              "name": "M274.920",
              "url": "https://mercedesengine.uk/engines/m274/"
            }
          ]
        },
        {
          "@type": "FAQPage",
          "mainEntity": [
            {
              "@type": "Question",
              "name": "How much does a Mercedes SLC 180 / 200 engine replacement cost in the UK?",
              "acceptedAnswer": {
                "@type": "Answer",
                "text": "A reconditioned SLC 180 engine typically costs £3,000–£5,500 supply only, while an SLC 200 engine costs £3,500–£6,500. Fitting adds £1,500–£2,500 depending on location and workshop rates. Main dealer new engines start from £8,000–£12,000+ supply only. Use our calculator for a figure specific to your car."
              }
            },
            {
              "@type": "Question",
              "name": "Is the Mercedes SLC 180 / 200 engine reliable?",
              "acceptedAnswer": {
                "@type": "Answer",
                "text": "The M274 is a generally solid and reliable engine. However, it has well-documented weaknesses: timing chain rattle on cold start is the most critical issue, PCV valve failure is a known design defect, thermostat failures are common, and oil leaks can damage the ECU. With proper maintenance, these engines can be reliable, but the timing chain issue is a genuine concern."
              }
            },
            {
              "@type": "Question",
              "name": "What are the common problems with the Mercedes SLC 180 / 200?",
              "acceptedAnswer": {
                "@type": "Answer",
                "text": "The main known issues are: (1) Timing chain rattle on cold start — the most critical and costly issue, requiring camshaft adjuster replacement, (2) PCV valve failure — a design defect causing fuel smell and potential turbo damage, (3) Thermostat and cooling system failures — causing temperature regulation issues, and (4) Oil leaks from valve cover gaskets and camshaft sensors — can damage the ECU."
              }
            },
            {
              "@type": "Question",
              "name": "Is it worth replacing a Mercedes SLC 180 / 200 engine, or should I scrap the car?",
              "acceptedAnswer": {
                "@type": "Answer",
                "text": "Depends on vehicle value and condition. Against a well-kept £10,000–£18,000 SLC, a £4,000–£5,500 recon is 20–55% of the car's value. For a clean example with full service history, replacement is often worth it given the SLC's strong retained values. However, if the car has other issues (roof mechanism, electrical faults), evaluate total repair costs before committing."
              }
            },
            {
              "@type": "Question",
              "name": "How do I find my Mercedes SLC 180 / 200 engine code?",
              "acceptedAnswer": {
                "@type": "Answer",
                "text": "Listed on the VIN plate and vehicle documentation. The SLC 180 uses the M274.910 (1.6L, 156 hp); the SLC 200 uses the M274.920 (2.0L, 184 hp). The engine code is stamped on the cylinder block. Tell us your registration and we'll confirm it for free."
              }
            },
            {
              "@type": "Question",
              "name": "Can I prevent timing chain issues on the M274?",
              "acceptedAnswer": {
                "@type": "Answer",
                "text": "Prevention is not guaranteed, but you can reduce the risk: (1) Change oil regularly using MB-approved oil — oil quality affects chain and tensioner life, (2) Use premium fuel (95/98 RON), (3) Listen for cold-start rattle — at the first sign, book an inspection immediately, and (4) Check for any outstanding recalls or technical bulletins on your vehicle."
              }
            }
          ]
        },
        {
          "@type": "Organization",
          "name": "MercedesEngine.uk",
          "url": "https://mercedesengine.uk/",
          "logo": "https://mercedesengine.uk/images/mercedesengine-logo.png",
          "parentOrganization": {
            "@type": "Organization",
            "name": "Engine Finders"
          }
        },
        {
          "@type": "Service",
          "serviceType": "Mercedes SLC 180/200 Engine Replacement",
          "provider": {
            "@type": "Organization",
            "name": "MercedesEngine.uk"
          },
          "areaServed": "GB",
          "offers": {
            "@type": "AggregateOffer",
            "priceCurrency": "GBP",
            "lowPrice": "1500",
            "highPrice": "6500",
            "availability": "https://schema.org/InStock"
          }
        },
        {
          "@type": "Dataset",
          "name": "Mercedes SLC 180/200 UK Engine Enquiry Data 2025",
          "description": "Proprietary UK enquiry volumes and demand trends for Mercedes SLC 180/200 engines, sourced from MercedesEngine.uk's specialist marketplace activity.",
          "creator": {
            "@type": "Organization",
            "name": "MercedesEngine.uk"
          },
          "temporalCoverage": "2025",
          "spatialCoverage": "United Kingdom"
        },
        {
          "@type": "WebPage",
          "name": "Mercedes SLC 180 / 200 Engine Replacement Cost UK — Compare Quotes",
          "url": "https://mercedesengine.uk/slc/slc180-200/",
          "author": {
            "@type": "Organization",
            "name": "MercedesEngine.uk Editorial Team"
          },
          "reviewedBy": {
            "@type": "Organization",
            "name": "MercedesEngine.uk Specialist Network"
          },
          "datePublished": "2026-07-12",
          "dateModified": "2026-07-12"
        }
      ]
    }
  },
  "hero": {
    "tagPill": "Mercedes SLC 180 / 200 • 2016–2020 • 1 Engine Generation (2 Displacements)",
    "h1": "Mercedes SLC 180 / 200 Engine Replacement — Compare Prices & Get Quotes",
    "subHeadline": "Get quotes today from trusted UK Mercedes SLC specialists. The SLC 180 and 200 share the M274 turbocharged four-cylinder family with different displacements — compare reconditioned, rebuilt and used engines with supply & fit available nationwide.",
    "trustBadges": [
      "🔧 Supply & Fit Available",
      "✅ 12-Month Warranty",
      "🚚 Nationwide Delivery",
      "👥 25+ Specialists"
    ],
    "priceAnchor": "Mercedes SLC 180 / 200 Engines — from £1,500 to £6,500 · Engine codes: M274.910, M274.920",
    "registrationInput": {
      "flag": "🇬🇧 GB",
      "placeholder": "Enter your reg — e.g. AB12 CDE",
      "cta": {
        "label": "Get My Free SLC Engine Quotes Now →",
        "href": "#"
      }
    },
    "ticker": "● Instant Quotes · No Obligation · 100% Free · Reconditioned · Rebuilt · Used · Supply & Fit Available · UK-Wide Network"
  },
  "eraMap": {
    "title": "Mercedes SLC 180 / 200 — Which Engine Does Your Car Actually Have?",
    "columns": [
      "Generation",
      "Years",
      "Engine Code",
      "Reliability",
      "Recon Cost",
      "Era Note"
    ],
    "rows": [
      {
        "generation": "R172 (SLC 180)",
        "years": "2016–2020",
        "engineCode": "M274.910 (1.6L)",
        "reliability": "★★★☆☆ [NEWLY ASSIGNED — see Data Note]",
        "reconCost": "£3,000–£5,500 [MB-QUOTE]",
        "eraNote": "1.6L turbo four-cylinder — 156 hp, 250 Nm. Efficient entry-level M274; timing chain tensioner and PCV issues documented"
      },
      {
        "generation": "R172 (SLC 200)",
        "years": "2016–2020",
        "engineCode": "M274.920 (2.0L)",
        "reliability": "★★★☆☆ [NEWLY ASSIGNED — see Data Note]",
        "reconCost": "£3,500–£6,500 [MB-QUOTE]",
        "eraNote": "2.0L turbo four-cylinder — 184 hp, 300 Nm. The M274 is generally reliable but has known weaknesses; timing chain rattle on cold start is the key concern"
      }
    ],
    "sourceNote": "",
    "dataNote": ""
  },
  "replacementCosts": {
    "h2": "Mercedes SLC 180 / 200 Engine Replacement Costs",
    "columns": [
      "Engine Type",
      "Supply Only",
      "Fitted (Indie)",
      "Warranty",
      "Best For"
    ],
    "rows": [
      {
        "engineType": "Used Engine",
        "supplyOnly": "£1,500–£3,000",
        "fittedIndie": "£2,500–£4,500",
        "warranty": "1–6 months",
        "bestFor": "Budget priority; lower-mileage donor"
      },
      {
        "engineType": "Reconditioned Engine",
        "supplyOnly": "£3,000–£5,500",
        "fittedIndie": "£4,500–£7,000",
        "warranty": "12–24 months",
        "bestFor": "Most owners — best cost/warranty balance"
      },
      {
        "engineType": "Rebuilt Engine",
        "supplyOnly": "£4,000–£6,500",
        "fittedIndie": "£5,500–£8,000",
        "warranty": "12–24 months",
        "bestFor": "Long-term ownership; 3+ year horizon"
      },
      {
        "engineType": "Main Dealer New",
        "supplyOnly": "£8,000–£12,000+",
        "fittedIndie": "£10,000–£14,000+",
        "warranty": "24–36 months",
        "bestFor": "Insurance jobs, warranty claims"
      }
    ],
    "figuresNote": "",
    "labourEstimate": "Fitting an SLC engine typically takes 12–16 hours at £65–£95/hr (independent) or £110–£160/hr (London/SE dealer). The M274's transverse layout and the SLC's compact engine bay add labour time.",
    "cta": {
      "label": "→ Compare SLC 180 / 200 engine prices from UK specialists",
      "href": "#"
    }
  },
  "commonProblems": {
    "problems": [
      {
        "id": 1,
        "title": "Timing Chain Rattle on Cold Start",
        "symptoms": "Metallic rattling or clattering noise for 2–3 seconds on cold start, noise that subsides as oil pressure builds, check engine light in later stages",
        "typicalMileage": "60,000–100,000 miles — a well-documented M274 weakness",
        "repairCost": "£800–£2,000 (camshaft adjuster sprockets and tensioner replacement)",
        "replacementCost": "£5,000–£8,000 (if chain jumps — full engine replacement)",
        "urgency": {
          "icon": "🔴",
          "label": "Immediate",
          "text": "if you hear rattling on cold start, book an inspection today"
        },
        "recommendation": "This is the most common issue on the M274 engine. The camshaft adjuster sprockets (phasers) wear, causing a metallic rattle on cold start for 2–3 seconds. If left unaddressed, the sprocket can break apart, the chain can jump, and valves will meet pistons — resulting in catastrophic engine failure. Mercedes recommends camshaft adjuster sprocket and chain tensioner replacement as the fix. A £800–£2,000 preventative repair is dramatically cheaper than a £5,000–£8,000 engine replacement. At the first sign of cold-start rattle, book an inspection immediately.",
        "failureLink": {
          "label": "Read the full timing chain failure guide → /failures/m274-timing-chain/ [NEW FAILURE PAGE NEEDED]",
          "href": "#"
        }
      },
      {
        "id": 2,
        "title": "PCV Valve Failure (Design Defect)",
        "symptoms": "Check engine light, fuel vapour smell in cabin, increased crankcase pressure, potential long-term turbo damage, whistling noise from the engine",
        "typicalMileage": "40,000–80,000 miles",
        "repairCost": "£300–£800 (PCV valve and breather system replacement)",
        "replacementCost": "£5,000–£8,000 (if ignored — can lead to turbo or engine damage)",
        "urgency": {
          "icon": "🟠",
          "label": "Check",
          "text": "book inspection urgently if you notice fuel smell or check engine light"
        },
        "recommendation": "The M274 PCV (Positive Crankcase Ventilation) valve has been acknowledged by Mercedes as a \"design defect\". Failure causes increased crankcase pressure, check engine lights, fuel vapour smell, and potential long-term turbo issues. If you notice a fuel smell in the cabin or a check engine light, have the PCV system inspected immediately. A £300–£800 repair is far cheaper than the turbo or engine damage that can follow if ignored.",
        "failureLink": {
          "label": "Read the full PCV valve failure guide → /failures/pcv-valve-failure/ [NEW FAILURE PAGE NEEDED]",
          "href": "#"
        }
      },
      {
        "id": 3,
        "title": "Thermostat & Cooling System Failure",
        "symptoms": "Engine running too cool (temperature stuck around 60–70°C), engine overheating, check engine light (P0128), increased fuel consumption",
        "typicalMileage": "50,000–100,000 miles",
        "repairCost": "£200–£600 (thermostat replacement)",
        "replacementCost": "N/A — repair only (does not progress to engine replacement if addressed)",
        "urgency": {
          "icon": "🟡",
          "label": "Monitor",
          "text": "book inspection if temperature issues develop"
        },
        "recommendation": "The M274's electronic thermostat is a common failure point. If it fails, the engine won't reach proper operating temperature or may overheat, triggering error code P0128. This increases fuel consumption and emissions. If you notice the temperature gauge not reaching normal operating range or erratic cooling, have the thermostat inspected. Replacing the thermostat with an OEM part is essential — aftermarket units often don't work correctly with the ECU.",
        "failureLink": {
          "label": "Read the full cooling system failure guide",
          "href": "/failures/cooling-system-failure/"
        }
      },
      {
        "id": 4,
        "title": "Oil Leaks & Carbon Buildup",
        "symptoms": "Burning oil smell, oil spots under the car, visible oil residue around the valve covers or camshaft sensors, rough idle, hesitation, misfires",
        "typicalMileage": "40,000–80,000 miles (carbon) / 60,000–100,000 miles (oil leaks)",
        "repairCost": "£400–£800 (valve cover gasket replacement) / £400–£800 (walnut blasting for carbon buildup)",
        "replacementCost": "N/A — repair only (does not progress to engine replacement if addressed)",
        "urgency": {
          "icon": "🟡",
          "label": "Monitor",
          "text": "book inspection if you notice oil spots or rough running"
        },
        "recommendation": "The M274 suffers from oil leaks through camshaft sensor seals, which can allow oil to travel into the wiring harness and damage the ECU. Valve cover gasket leaks are also common. Preventive measures like oil-stop wiring can help avoid costly repairs. Additionally, the M274's direct injection system causes carbon buildup on intake valves, leading to rough idle and hesitation. Regular valve cleaning and using fuel additives can help maintain performance.",
        "failureLink": {
          "label": "Read the full oil leak guide → /failures/m274-oil-leaks/ [NEW FAILURE PAGE NEEDED]",
          "href": "#"
        }
      }
    ]
  },
  "quotesCta": {
    "headline": "Ready to Compare? Get Matched With a Vetted Mercedes Specialist →",
    "supportingLine": "25+ vetted Mercedes specialists, every SLC 180/200 engine covered, with a 12-month warranty as standard.",
    "button": {
      "label": "Get My Free SLC Engine Quotes Now →",
      "href": "#"
    }
  },
  "repairBuyOrReplace": {
    "h2": "SLC 180 / 200 — Repair, Buy, or Replace?",
    "canItBeRepaired": {
      "title": "Can It Be Repaired?",
      "columns": [
        "Problem",
        "Repairable?",
        "Typical Cost",
        "When It Makes Sense"
      ],
      "rows": [
        {
          "problem": "Timing chain rattle (early detection)",
          "repairable": "✅ Yes",
          "typicalCost": "£800–£2,000",
          "whenItMakesSense": "Preventative — catches the fault before catastrophic failure"
        },
        {
          "problem": "Timing chain jumped",
          "repairable": "❌ Usually No",
          "typicalCost": "Engine replacement",
          "whenItMakesSense": "Full engine replacement is the only reliable fix"
        },
        {
          "problem": "PCV valve failure",
          "repairable": "✅ Yes",
          "typicalCost": "£300–£800",
          "whenItMakesSense": "Catch early to prevent turbo and engine damage"
        },
        {
          "problem": "Thermostat / cooling system failure",
          "repairable": "✅ Yes",
          "typicalCost": "£200–£600",
          "whenItMakesSense": "Straightforward component replacement"
        },
        {
          "problem": "Oil leaks / carbon buildup",
          "repairable": "✅ Yes",
          "typicalCost": "£400–£800",
          "whenItMakesSense": "Catch early to prevent ECU and engine damage"
        }
      ]
    },
    "buyingChecks": {
      "title": "Buying This SLC 180 / 200? Check These First",
      "buyIf": [
        "* Full service history with regular oil changes using MB-approved oil",
        "* No cold-start rattling — this is a critical warning sign",
        "* Documented timing chain and camshaft adjuster work",
        "* Post-2016 M274 with updated components",
        "* Remainder of manufacturer warranty or extended warranty in place"
      ],
      "avoidIf": [
        "* Cold-start rattle with no documented timing chain work",
        "* Check engine light with fuel smell — PCV valve failure",
        "* Poor service history — the M274 is a good engine but needs proper maintenance",
        "* Thermostat or cooling system warning codes"
      ]
    },
    "closingVerdict": "The SLC 180 and SLC 200 share the M274 turbocharged four-cylinder engine family — a generally solid and reliable unit that powers a wide range of Mercedes models. However, it has well-documented weaknesses: timing chain rattle on cold start is the most critical and costly issue, PCV valve failure is a known design defect, thermostat failures are common, and oil leaks can damage the ECU. Buy a well-maintained example with full service history and no rattling. Without history? Proceed with caution — the repair bills can be substantial.",
    "cta": {
      "label": "→ Compare SLC 180 / 200 engine prices before you buy",
      "href": "#"
    }
  },
  "buyingChecklist": {
    "intro": "Before you buy a used Mercedes SLC 180 or SLC 200 (or before you commit to an engine replacement), check these:",
    "items": [
      "* Cold Start — Listen for rattling or clattering for 2–3 seconds (timing chain tensioner / camshaft adjuster warning — this is critical)",
      "* Fuel Smell — Any fuel vapour smell in the cabin? (PCV valve failure)",
      "* Temperature Gauge — Does it reach normal operating temperature? (Thermostat failure)",
      "* Service History — Including the M274 engine and confirmed oil-interval discipline",
      "* Oil Leaks — Look for oil residue around the valve covers and camshaft sensors",
      "* Engine Warning Light — Have codes been read? Look for timing, thermostat or PCV-related codes",
      "* Roof Mechanism — Check the Vario-roof operation; hydraulic leaks and microswitch failures are common",
      "* MOT History — Check for emissions-related failures"
    ]
  },
  "engineCodes": {
    "columns": [
      "Engine Code",
      "Years",
      "Power",
      "2025 Enquiries",
      "Avg. Recon Cost"
    ],
    "rows": [
      {
        "engineCode": "M274.910 (SLC 180)",
        "years": "2016–2020",
        "power": "156 hp (115 kW) / 250 Nm",
        "enquiries": "— (pattern data)",
        "avgReconCost": "£3,000–£5,500【MB-QUOTE】"
      },
      {
        "engineCode": "M274.920 (SLC 200)",
        "years": "2016–2020",
        "power": "184 hp (135 kW) / 300 Nm",
        "enquiries": "— (pattern data)",
        "avgReconCost": "£3,500–£6,500【MB-QUOTE】"
      }
    ],
    "matchNote": "This table's rows match Section 1B's Era Map exactly.",
    "technicalSpecs": {
      "title": "Technical Specs (M274.910 — SLC 180):",
      "items": [
        {
          "label": "* Displacement",
          "value": "1,991 cc (2.0L)"
        },
        {
          "label": "* Cylinders",
          "value": "4-cylinder inline"
        },
        {
          "label": "* Bore",
          "value": "83.0 mm"
        },
        {
          "label": "* Compression Ratio",
          "value": "10.3:1"
        },
        {
          "label": "* Fuel System",
          "value": "Direct injection"
        },
        {
          "label": "* Turbocharger",
          "value": "Single turbo"
        },
        {
          "label": "* Valvetrain",
          "value": "DOHC, 4 valves per cylinder, chain-driven"
        },
        {
          "label": "* Power",
          "value": "135 kW (184 PS) @ 5,500 rpm"
        },
        {
          "label": "* Torque",
          "value": "300 Nm @ 1,200–4,000 rpm"
        },
        {
          "label": "* 0-100 km/h",
          "value": "~7.3 seconds"
        },
        {
          "label": "* Top Speed",
          "value": "235 km/h"
        },
        {
          "label": "* Transmission",
          "value": "6-speed manual / 9G-TRONIC automatic"
        },
        {
          "label": "* Displacement",
          "value": "1,595 cc (1.6L)"
        },
        {
          "label": "* Cylinders",
          "value": "4-cylinder inline"
        },
        {
          "label": "* Bore",
          "value": "83.0 mm / Stroke: 73.7 mm"
        },
        {
          "label": "* Power",
          "value": "115 kW (156 hp) @ 5,300 rpm"
        },
        {
          "label": "* Torque",
          "value": "250 Nm @ 1,200–4,000 rpm"
        },
        {
          "label": "* Transmission",
          "value": "6-speed manual / 9G-TRONIC automatic"
        }
      ]
    },
    "cta": {
      "label": "→ Compare SLC 180 / 200 engine prices for your Mercedes",
      "href": "#"
    }
  },
  "marketIntelligence": {
    "items": []
  },
  "faq": {
    "items": [
      {
        "id": 1,
        "question": "How much does a Mercedes SLC 180 / 200 engine replacement cost in the UK?",
        "answer": "A reconditioned SLC 180 engine typically costs £3,000–£5,500 supply only, while an SLC 200 engine costs £3,500–£6,500. Fitting adds £1,500–£2,500 depending on location and workshop rates. Main dealer new engines start from £8,000–£12,000+ supply only. Use our calculator for a figure specific to your car."
      },
      {
        "id": 2,
        "question": "Is the Mercedes SLC 180 / 200 engine reliable?",
        "answer": "The M274 is a generally solid and reliable engine. However, it has well-documented weaknesses: timing chain rattle on cold start is the most critical issue, PCV valve failure is a known design defect, thermostat failures are common, and oil leaks can damage the ECU. With proper maintenance, these engines can be reliable, but the timing chain issue is a genuine concern."
      },
      {
        "id": 3,
        "question": "What are the common problems with the Mercedes SLC 180 / 200?",
        "answer": "The main known issues are: (1) Timing chain rattle on cold start — the most critical and costly issue, requiring camshaft adjuster replacement, (2) PCV valve failure — a design defect causing fuel smell and potential turbo damage, (3) Thermostat and cooling system failures — causing temperature regulation issues, and (4) Oil leaks from valve cover gaskets and camshaft sensors — can damage the ECU."
      },
      {
        "id": 4,
        "question": "Is it worth replacing a Mercedes SLC 180 / 200 engine, or should I scrap the car?",
        "answer": "Depends on vehicle value and condition. Against a well-kept £10,000–£18,000 SLC, a £4,000–£5,500 recon is 20–55% of the car's value. For a clean example with full service history, replacement is often worth it given the SLC's strong retained values. However, if the car has other issues (roof mechanism, electrical faults), evaluate total repair costs before committing."
      },
      {
        "id": 5,
        "question": "How do I find my Mercedes SLC 180 / 200 engine code?",
        "answer": "Listed on the VIN plate and vehicle documentation. The SLC 180 uses the M274.910 (1.6L, 156 hp); the SLC 200 uses the M274.920 (2.0L, 184 hp). The engine code is stamped on the cylinder block. Tell us your registration and we'll confirm it for free."
      },
      {
        "id": 6,
        "question": "Can I prevent timing chain issues on the M274?",
        "answer": "Prevention is not guaranteed, but you can reduce the risk: (1) Change oil regularly using MB-approved oil — oil quality affects chain and tensioner life, (2) Use premium fuel (95/98 RON), (3) Listen for cold-start rattle — at the first sign, book an inspection immediately, and (4) Check for any outstanding recalls or technical bulletins on your vehicle. A £800–£2,000 preventative repair is far cheaper than a £5,000–£8,000 engine replacement."
      }
    ],
    "disclaimer": "All prices are indicative UK market ranges based on historical quote data from our network of engine specialists. Actual costs vary by variant, engine code, damage severity and workshop location. Use our free comparison tool to get tailored quotes. Every engine supplied through EnginesMarket carries a minimum 12-month unlimited-mileage warranty — always confirm terms with your chosen supplier."
  },
  "trustCta": {
    "h2": "Why UK Mercedes SLC 180 / 200 Owners Trust MercedesEngine.uk",
    "trustPoints": [
      {
        "title": "Trusted SLC 180/200 Engine Suppliers",
        "text": "every garage and engine rebuilder in our network is vetted, rated and reviewed by real SLC owners, across both M274.910 and M274.920 variants, as part of the Engine Finders network."
      },
      {
        "title": "Compare SLC Engine Replacement Companies",
        "text": "see prices, warranty terms and supply & fit options side-by-side before you commit."
      },
      {
        "title": "UK Engine Replacement Services for SLC 180/200",
        "text": "supply-only or full supply & fit available nationwide, covering every R172 SLC since 2016."
      }
    ],
    "finalCta": "Find the best Mercedes SLC 180 / 200 engine replacement UK drivers rely on. Compare prices from trusted specialists on EnginesMarket today and get back on the road with confidence.",
    "ctaButton": {
      "label": "Compare Mercedes SLC 180 / 200 Engine Prices Now →",
      "href": "#"
    }
  }
}
